{"skeleton":{"hash":"kJGfZOlUFrQiJmwzTIlyjHugNAc","spine":"3.6.37","width":291.17,"height":364.74},"bones":[{"name":"root","x":-3.7,"y":53.45},{"name":"center","parent":"root","x":1.62,"y":-29.94},{"name":"Accessery","parent":"center","length":36.98,"rotation":-100.23,"x":-50.65,"y":64.31},{"name":"Body","parent":"center","length":55.07,"rotation":-88.26,"x":-1.67,"y":30.02},{"name":"UpperArmL","parent":"Body","length":45.57,"rotation":-147.17,"x":-5.61,"y":-47.39},{"name":"LowerArmL","parent":"UpperArmL","length":51.87,"rotation":-56.51,"x":45.57},{"name":"HandL","parent":"LowerArmL","length":10,"x":52.45,"y":0.07},{"name":"UpperArmR","parent":"Body","length":45.14,"rotation":48.74,"x":5.65,"y":48.22},{"name":"LowerArmR","parent":"UpperArmR","length":42.24,"rotation":47.1,"x":45.14},{"name":"HandR","parent":"LowerArmR","length":10,"rotation":17.06,"x":42.95,"y":0.48},{"name":"Head","parent":"center","length":58.48,"rotation":86.73,"x":5,"y":42.53},{"name":"ShootPos","parent":"Body","rotation":-91.74,"x":-73.41,"y":5.97},{"name":"Telescope","parent":"center","length":79.94,"rotation":88.57,"x":1.25,"y":127.55},{"name":"WeaponL","parent":"HandR","length":50,"rotation":59.13,"x":6.66,"y":0.11},{"name":"WeaponR","parent":"HandL","length":50,"rotation":-59.32,"x":5.77,"y":-0.15}],"slots":[{"name":"Telescope","bone":"Telescope","color":"ffffff00","attachment":"Telescope"},{"name":"Body","bone":"Body","attachment":"Body"},{"name":"WeaponL","bone":"WeaponL","attachment":"sabersheath"},{"name":"Accessery","bone":"Accessery","attachment":"saber"},{"name":"HandL","bone":"HandL","attachment":"HandL"},{"name":"UpperArmL","bone":"UpperArmL","attachment":"UpperArmL"},{"name":"HandR","bone":"HandR","attachment":"HandR"},{"name":"UpperArmR","bone":"UpperArmR","attachment":"UpperArmR"},{"name":"Head","bone":"Head","attachment":"Head"},{"name":"WeaponR","bone":"WeaponR"}],"skins":{"default":{"Accessery":{"saber":{"x":109.95,"y":6.84,"rotation":-177.76,"width":198,"height":39},"sword_sheath":{"x":97.86,"y":1.14,"rotation":-178.08,"width":219,"height":19}},"Body":{"Body":{"x":19.48,"y":1.32,"rotation":88.26,"width":146,"height":115}},"HandL":{"HandL":{"x":0.44,"y":-0.44,"rotation":56.51,"width":26,"height":24}},"HandR":{"HandR":{"x":3.45,"y":0.04,"rotation":-33.53,"width":26,"height":24}},"Head":{"Head":{"x":8.8,"y":4.77,"rotation":-86.73,"width":113,"height":125}},"Telescope":{"Telescope":{"x":36.46,"y":0.48,"rotation":-88.57,"width":119,"height":91}},"UpperArmL":{"UpperArmL":{"type":"mesh","path":"ArmL","uvs":[0.52144,0,0.90531,0,0.93959,0.13901,0.82991,0.24441,0.7408,0.3566,0.74765,0.4756,0.91902,0.547,1,0.6524,1,0.8734,0.82306,1,0.44604,1,0.13072,0.9346,0,0.785,0,0.5674,0,0.4178,0.06903,0.29881,0.09645,0.16621,0.42548,0.02681,0.67225,0.8054,0.37749,0.5402,0.49403,0.19341,0.61741,0.11861],"triangles":[14,15,19,19,15,20,19,20,4,20,15,16,20,21,4,4,21,3,2,3,1,16,17,20,20,0,21,20,17,0,3,21,1,21,0,1,10,18,9,9,18,8,18,10,19,10,11,19,11,12,19,18,7,8,18,6,7,18,5,6,18,19,5,12,13,19,13,14,19,19,4,5],"vertices":[1,5,63.13,12.9,1,1,5,72.02,-9.18,1,1,5,56.7,-17.64,1,2,4,55.15,-43.95,7.0E-5,5,41.94,-16.26,0.99993,2,4,46.74,-31.44,0.06304,5,26.86,-16.38,0.93696,2,4,34.25,-23.35,0.55269,5,13.23,-22.33,0.44731,2,4,20.87,-27.04,0.90718,5,8.92,-35.52,0.09282,2,4,7.17,-23.7,0.98815,5,-1.42,-45.1,0.01185,1,4,-15.58,-8.03,1,1,4,-22.39,9.98,1,1,4,-9.13,29.23,1,1,4,8.7,40.69,1,1,4,28.69,36.76,1,2,4,51.09,21.33,0.74711,5,-14.74,16.37,0.25289,2,4,66.49,10.72,0.10453,5,2.6,23.36,0.89547,1,5,18,24.95,1,1,5,34.01,29.57,1,1,5,57.79,17.16,1,1,4,2.95,3.88,1,1,4,40.62,0.13,1,1,5,40.07,5.44,1,1,5,51.6,1.84,1],"hull":18}},"UpperArmR":{"UpperArmR":{"type":"mesh","path":"ArmR","uvs":[0.14105,0,0.47694,0,0.77169,0.10841,0.9225,0.27501,1,0.445,1,0.6218,1,0.7646,0.85395,0.9482,0.56605,1,0.18903,0.9958,0,0.904,0,0.7476,0,0.615,0.14791,0.513,0.27815,0.4416,0.27815,0.37361,0.20274,0.32261,0.16162,0.21721,0.08621,0.15941,0.05879,0.05741,0.31928,0.8122,0.62774,0.53,0.44952,0.15601,0.29186,0.09141],"triangles":[21,15,22,21,3,4,21,2,3,21,22,2,22,15,23,15,16,23,16,17,23,17,18,23,18,0,23,18,19,0,22,1,2,22,23,1,23,0,1,9,20,8,7,8,21,9,10,20,8,20,21,7,21,6,10,11,20,11,13,20,13,14,20,20,14,21,21,5,6,11,12,13,21,4,5,21,14,15],"vertices":[1,8,63.5,9.31,1,1,8,56.52,-10.31,1,1,8,37.62,-22.98,1,2,7,73.43,-5.99,0.00927,8,14.87,-24.8,0.99073,2,7,56.8,-20.07,0.4562,8,-6.76,-22.2,0.5438,2,7,37.2,-30.28,0.96835,8,-27.58,-14.79,0.03165,1,7,21.37,-38.52,1,1,7,-3.17,-41.09,1,1,7,-17.16,-28.25,1,1,7,-27.49,-7.28,1,1,7,-22.73,8.42,1,1,7,-5.39,17.45,1,2,7,9.31,25.1,0.99925,8,-5.99,43.33,7.5E-4,2,7,24.86,22.86,0.9321,8,2.94,30.42,0.0679,2,7,36.5,19.82,0.58296,8,8.64,19.82,0.41704,2,7,44.04,23.75,0.16347,8,16.65,16.97,0.83653,2,7,47.54,30.84,0.03053,8,24.22,19.23,0.96947,1,8,37.49,17.22,1,1,8,45.87,19.2,1,1,8,58.45,16.53,1,1,7,-3.41,-3.84,1,1,7,36.71,-4.51,1,1,8,38.71,-2.16,1,1,8,49.6,4.34,1],"hull":20}},"WeaponL":{"sabersheath":{"x":80.34,"y":-6.44,"rotation":177.71,"width":261,"height":61},"sword":{"x":98.18,"y":-0.58,"rotation":179.3,"width":297,"height":78}}}},"events":{"Attack":{"string":"Attack"},"Skill":{}},"animations":{"Attack":{"slots":{"WeaponL":{"attachment":[{"time":0,"name":"sabersheath"}]}},"bones":{"Body":{"rotate":[{"time":0,"angle":32.81},{"time":0.1333,"angle":80.93},{"time":0.3333,"angle":-28},{"time":1,"angle":32.81}],"translate":[{"time":0,"x":0,"y":0},{"time":0.1333,"x":0,"y":-15.08},{"time":0.3333,"x":18.82,"y":30.16},{"time":1,"x":0,"y":0}]},"UpperArmR":{"rotate":[{"time":0,"angle":0},{"time":0.1333,"angle":-217.82},{"time":0.3333,"angle":52.85},{"time":1,"angle":0}],"translate":[{"time":0,"x":0,"y":0,"curve":"stepped"},{"time":0.1333,"x":0,"y":0},{"time":0.3333,"x":-18.78,"y":-13.93},{"time":1,"x":0,"y":0}]},"LowerArmR":{"rotate":[{"time":0,"angle":0},{"time":0.1333,"angle":-16.89},{"time":0.3333,"angle":-31.94},{"time":1,"angle":0}],"translate":[{"time":0,"x":0,"y":0,"curve":"stepped"},{"time":0.1333,"x":0,"y":0,"curve":"stepped"},{"time":1,"x":0,"y":0}]},"WeaponL":{"rotate":[{"time":0,"angle":-43.73},{"time":0.1333,"angle":-13.66},{"time":0.3333,"angle":-51.57},{"time":1,"angle":-43.73}]},"UpperArmL":{"rotate":[{"time":0,"angle":0},{"time":0.1333,"angle":-17.17},{"time":0.3333,"angle":60.78},{"time":0.6,"angle":55.59},{"time":1,"angle":0}]},"Accessery":{"rotate":[{"time":0,"angle":22.98},{"time":0.1333,"angle":65.06},{"time":0.4,"angle":10.69},{"time":1,"angle":22.98}],"translate":[{"time":0,"x":-8.23,"y":-5.48},{"time":0.1333,"x":17.82,"y":-82.78},{"time":0.4,"x":0.84,"y":42.53},{"time":1,"x":-8.23,"y":-5.48}]},"Head":{"rotate":[{"time":0,"angle":0,"curve":"stepped"},{"time":0.1333,"angle":0},{"time":0.3333,"angle":16.19},{"time":1,"angle":0}],"translate":[{"time":0,"x":0,"y":1.77},{"time":0.1333,"x":0,"y":-8.86},{"time":0.3333,"x":0,"y":30.82},{"time":1,"x":0,"y":1.77}]}},"events":[{"time":0.3333,"name":"Attack"}]},"Attack_thrush":{"slots":{"Accessery":{"attachment":[{"time":0,"name":"sword_sheath"}]}},"bones":{"Body":{"rotate":[{"time":0,"angle":32.81},{"time":0.1333,"angle":-17.83},{"time":0.3333,"angle":45.55},{"time":1,"angle":32.81}],"translate":[{"time":0,"x":0,"y":0},{"time":0.1333,"x":0,"y":-15.08},{"time":0.3333,"x":0,"y":30.16},{"time":1,"x":0,"y":0}]},"UpperArmR":{"rotate":[{"time":0,"angle":0},{"time":0.1333,"angle":-9.98},{"time":0.3333,"angle":70.51},{"time":1,"angle":0}],"translate":[{"time":0,"x":0,"y":0,"curve":"stepped"},{"time":0.1333,"x":0,"y":0,"curve":"stepped"},{"time":0.3333,"x":0,"y":0,"curve":"stepped"},{"time":1,"x":0,"y":0}]},"LowerArmR":{"rotate":[{"time":0,"angle":0},{"time":0.1333,"angle":37.13},{"time":0.3333,"angle":-24.44},{"time":1,"angle":0}],"translate":[{"time":0,"x":0,"y":0,"curve":"stepped"},{"time":0.1333,"x":0,"y":0,"curve":"stepped"},{"time":1,"x":0,"y":0}]},"WeaponL":{"rotate":[{"time":0,"angle":0},{"time":0.1333,"angle":-13.66},{"time":0.3333,"angle":-58.43},{"time":1,"angle":0}]},"UpperArmL":{"rotate":[{"time":0,"angle":0},{"time":0.1333,"angle":-17.17},{"time":0.3333,"angle":60.78},{"time":0.6,"angle":55.59},{"time":1,"angle":0}]},"Accessery":{"rotate":[{"time":0,"angle":22.98},{"time":0.1333,"angle":-25.29},{"time":0.4,"angle":48.8},{"time":1,"angle":22.98}],"translate":[{"time":0,"x":-8.23,"y":-5.48},{"time":0.1333,"x":17.82,"y":-9.6},{"time":0.4,"x":0.84,"y":-26.47},{"time":1,"x":-8.23,"y":-5.48}]},"Head":{"rotate":[{"time":0,"angle":0,"curve":"stepped"},{"time":0.1333,"angle":0},{"time":0.3333,"angle":16.19},{"time":1,"angle":0}],"translate":[{"time":0,"x":0,"y":1.77},{"time":0.1333,"x":0,"y":-8.86},{"time":0.3333,"x":0,"y":30.82},{"time":1,"x":0,"y":1.77}]}},"events":[{"time":0.3333,"name":"Attack"}]},"Dead":{"slots":{"WeaponL":{"attachment":[{"time":0,"name":"sabersheath"}]}},"bones":{"Body":{"rotate":[{"time":0,"angle":0,"curve":"stepped"},{"time":0.0667,"angle":0}],"translate":[{"time":0,"x":0,"y":0},{"time":0.0667,"x":0,"y":-23.31},{"time":0.2667,"x":0,"y":-15.08},{"time":0.4333,"x":0,"y":41.13,"curve":"stepped"},{"time":1,"x":0,"y":41.13}],"scale":[{"time":0,"x":1,"y":1}]},"Head":{"rotate":[{"time":0,"angle":0}],"translate":[{"time":0,"x":0,"y":0},{"time":0.1333,"x":0,"y":-41.13},{"time":0.4333,"x":0,"y":74.03}],"scale":[{"time":0,"x":1,"y":1}]},"UpperArmL":{"rotate":[{"time":0,"angle":0},{"time":0.0667,"angle":48.26,"curve":"stepped"},{"time":0.3333,"angle":48.26},{"time":0.5,"angle":-13.3}],"translate":[{"time":0,"x":0,"y":0,"curve":"stepped"},{"time":0.0667,"x":0,"y":0}]},"UpperArmR":{"rotate":[{"time":0,"angle":0},{"time":0.0667,"angle":-22.17,"curve":"stepped"},{"time":0.3333,"angle":-22.17},{"time":0.5,"angle":102.24}],"translate":[{"time":0,"x":0,"y":0,"curve":"stepped"},{"time":0.0667,"x":0,"y":0,"curve":"stepped"},{"time":0.3333,"x":0,"y":0},{"time":0.5,"x":-17.81,"y":0.54}]},"WeaponL":{"rotate":[{"time":0,"angle":0,"curve":"stepped"},{"time":0.0667,"angle":0,"curve":"stepped"},{"time":0.4333,"angle":0},{"time":0.5,"angle":2.83},{"time":0.6667,"angle":38.78}],"translate":[{"time":0,"x":0,"y":0},{"time":0.5,"x":-0.44,"y":-1.22},{"time":0.6667,"x":70.88,"y":-44.89},{"time":0.7333,"x":80.66,"y":-48.42,"curve":"stepped"},{"time":1,"x":80.66,"y":-48.42}]},"Accessery":{"rotate":[{"time":0,"angle":0},{"time":0.0667,"angle":8.53},{"time":0.4333,"angle":-3.26},{"time":0.5,"angle":3.19},{"time":0.5667,"angle":1.19}],"translate":[{"time":0,"x":0,"y":0},{"time":0.0667,"x":-1.37,"y":-35.65},{"time":0.4333,"x":-13.71,"y":37.02},{"time":0.5,"x":-21.94,"y":37.02}]}}},"Idle":{"slots":{"WeaponL":{"attachment":[{"time":0,"name":"sabersheath"}]}},"bones":{"UpperArmL":{"rotate":[{"time":0,"angle":0},{"time":0.5,"angle":-11.93},{"time":1,"angle":0}]},"Body":{"translate":[{"time":0,"x":0,"y":0},{"time":0.5,"x":0,"y":-3.27},{"time":1,"x":0,"y":0}]},"LowerArmL":{"rotate":[{"time":0,"angle":0},{"time":0.5,"angle":-5.17},{"time":1,"angle":0}]},"UpperArmR":{"rotate":[{"time":0,"angle":0},{"time":0.5,"angle":-2.3},{"time":1,"angle":0}]},"LowerArmR":{"rotate":[{"time":0,"angle":0},{"time":0.5,"angle":9.07},{"time":1,"angle":0}]},"Accessery":{"translate":[{"time":0,"x":0,"y":0},{"time":0.5,"x":0,"y":-2.18},{"time":1,"x":0,"y":0}]},"Head":{"translate":[{"time":0,"x":0,"y":0},{"time":0.5,"x":0,"y":3.27},{"time":1,"x":0,"y":0}]}}},"Move":{"slots":{"WeaponL":{"attachment":[{"time":0.5333,"name":"sabersheath"}]}},"bones":{"Body":{"rotate":[{"time":0,"angle":0},{"time":0.2667,"angle":-4.82},{"time":0.5,"angle":0},{"time":0.7333,"angle":3.66},{"time":1,"angle":0}]},"Head":{"translate":[{"time":0,"x":0,"y":0},{"time":0.2667,"x":0,"y":6.26},{"time":0.5,"x":0,"y":0},{"time":0.7333,"x":0,"y":5.01},{"time":1,"x":0,"y":0}]},"Accessery":{"rotate":[{"time":0,"angle":0},{"time":0.2667,"angle":-5.99},{"time":0.7333,"angle":2.81},{"time":1,"angle":0}],"translate":[{"time":0,"x":0,"y":0},{"time":0.2667,"x":0,"y":7.52},{"time":0.5,"x":0,"y":0},{"time":0.7333,"x":0,"y":-8.77},{"time":1,"x":0,"y":0}]}}},"Ride":{"slots":{"Telescope":{"color":[{"time":0,"color":"ffffff00"}]},"WeaponL":{"color":[{"time":0.1,"color":"ffffff00"}]}},"bones":{"UpperArmR":{"rotate":[{"time":0,"angle":104.42},{"time":0.1667,"angle":92.13}],"translate":[{"time":0,"x":-8.79,"y":0.27}]},"UpperArmL":{"rotate":[{"time":0,"angle":-5.29},{"time":0.1667,"angle":4.01}],"translate":[{"time":0,"x":0.27,"y":8.79}]},"Telescope":{"translate":[{"time":0,"x":1.76,"y":-8.79},{"time":0.1667,"x":1.76,"y":-41.31}]},"LowerArmL":{"rotate":[{"time":0,"angle":0},{"time":0.1667,"angle":-26.77}]},"LowerArmR":{"rotate":[{"time":0,"angle":0},{"time":0.1667,"angle":27.55,"curve":"stepped"},{"time":0.5,"angle":27.55}]}}},"Skill1":{"slots":{"WeaponL":{"attachment":[{"time":0.8333,"name":"sabersheath"}]}},"bones":{"Body":{"rotate":[{"time":0,"angle":0},{"time":0.2333,"angle":-56.23},{"time":0.3333,"angle":64.51,"curve":"stepped"},{"time":0.7333,"angle":64.51},{"time":1,"angle":0}],"translate":[{"time":0,"x":0,"y":0,"curve":"stepped"},{"time":0.2333,"x":0,"y":0},{"time":0.3333,"x":0,"y":70.89},{"time":0.7333,"x":0,"y":72.81},{"time":1,"x":0,"y":0}]},"UpperArmR":{"rotate":[{"time":0,"angle":0,"curve":"stepped"},{"time":0.2333,"angle":0},{"time":0.3333,"angle":48.92,"curve":"stepped"},{"time":0.7333,"angle":48.92},{"time":1,"angle":0}]},"LowerArmR":{"rotate":[{"time":0,"angle":0},{"time":0.2333,"angle":46.26},{"time":0.3333,"angle":-36.95,"curve":"stepped"},{"time":0.7333,"angle":-36.95},{"time":1,"angle":0}]},"WeaponL":{"rotate":[{"time":0,"angle":0},{"time":0.2333,"angle":15.09},{"time":0.3333,"angle":-52.13,"curve":"stepped"},{"time":0.7333,"angle":-52.13},{"time":1,"angle":0}]},"Head":{"rotate":[{"time":0,"angle":0},{"time":0.2333,"angle":-16.31},{"time":0.3333,"angle":39.73,"curve":"stepped"},{"time":0.7333,"angle":39.73},{"time":1,"angle":0}],"translate":[{"time":0,"x":0,"y":0},{"time":0.2333,"x":3.83,"y":-19.16},{"time":0.3333,"x":3.32,"y":96.44,"curve":"stepped"},{"time":0.7333,"x":3.32,"y":96.44},{"time":1,"x":0,"y":0}]},"UpperArmL":{"rotate":[{"time":0,"angle":0},{"time":0.2333,"angle":-10.96},{"time":0.3333,"angle":82.73,"curve":"stepped"},{"time":0.7333,"angle":82.73},{"time":1,"angle":0}],"translate":[{"time":0,"x":0,"y":0,"curve":"stepped"},{"time":0.2333,"x":0,"y":0},{"time":0.3333,"x":-6.17,"y":14.03,"curve":"stepped"},{"time":0.7333,"x":-6.17,"y":14.03},{"time":1,"x":0,"y":0}]},"Accessery":{"rotate":[{"time":0,"angle":0.17},{"time":0.2333,"angle":-30.9},{"time":0.3333,"angle":71,"curve":"stepped"},{"time":0.7333,"angle":71},{"time":1,"angle":0.17}],"translate":[{"time":0,"x":0,"y":0},{"time":0.2333,"x":19.16,"y":7.66},{"time":0.3333,"x":14.69,"y":12.39,"curve":"stepped"},{"time":0.7333,"x":14.69,"y":12.39},{"time":1,"x":0,"y":0}]}},"events":[{"time":0.3333,"name":"Skill","string":"Skill"}]},"Skill2":{"slots":{"WeaponL":{"attachment":[{"time":0.8667,"name":"sabersheath"}]}},"bones":{"Body":{"rotate":[{"time":0,"angle":35.21},{"time":0.5,"angle":38.41},{"time":1,"angle":35.21}]},"UpperArmR":{"rotate":[{"time":0,"angle":59.59},{"time":0.5,"angle":64.31},{"time":1,"angle":59.59}]},"LowerArmR":{"rotate":[{"time":0,"angle":-10.24},{"time":0.5,"angle":-18.64},{"time":1,"angle":-10.24}]},"UpperArmL":{"rotate":[{"time":0,"angle":40.28},{"time":0.5,"angle":47.38},{"time":1,"angle":40.28}]},"WeaponL":{"rotate":[{"time":0,"angle":0,"curve":"stepped"},{"time":1,"angle":0}],"translate":[{"time":0,"x":0,"y":0,"curve":"stepped"},{"time":1,"x":0,"y":0}]},"Accessery":{"rotate":[{"time":0,"angle":22.68},{"time":0.5,"angle":26.57},{"time":1,"angle":22.68}],"translate":[{"time":0,"x":1.92,"y":-17.24},{"time":0.5,"x":-3.83,"y":-17.24},{"time":1,"x":1.92,"y":-17.24}]}}},"Skill3":{"bones":{"Body":{"rotate":[{"time":0,"angle":0},{"time":0.1333,"angle":-21.78,"curve":"stepped"},{"time":0.2667,"angle":-21.78},{"time":0.4333,"angle":5.91,"curve":"stepped"},{"time":0.5667,"angle":5.91,"curve":"stepped"},{"time":0.6667,"angle":5.91},{"time":0.7667,"angle":-36.87},{"time":0.9667,"angle":-32.26},{"time":1.0333,"angle":0}],"translate":[{"time":0,"x":0,"y":0,"curve":"stepped"},{"time":0.1333,"x":0,"y":0,"curve":"stepped"},{"time":0.2667,"x":0,"y":0,"curve":"stepped"},{"time":0.4333,"x":0,"y":0,"curve":"stepped"},{"time":0.5667,"x":0,"y":0,"curve":"stepped"},{"time":0.6667,"x":0,"y":0,"curve":"stepped"},{"time":0.7667,"x":0,"y":0,"curve":"stepped"},{"time":0.9667,"x":0,"y":0,"curve":"stepped"},{"time":1.0333,"x":0,"y":0}]},"Head":{"rotate":[{"time":0,"angle":0},{"time":0.1333,"angle":-47.24},{"time":0.2667,"angle":-6.56},{"time":0.4333,"angle":23.9},{"time":0.5667,"angle":6.93,"curve":"stepped"},{"time":0.6667,"angle":6.93},{"time":1.0333,"angle":0}],"translate":[{"time":0,"x":0,"y":0},{"time":0.1333,"x":0,"y":-12.55},{"time":0.2667,"x":0,"y":-10.04},{"time":0.4333,"x":0,"y":11.29},{"time":0.5667,"x":0,"y":7.53,"curve":"stepped"},{"time":0.6667,"x":0,"y":7.53},{"time":0.7667,"x":0,"y":-29.53},{"time":1.0333,"x":0,"y":0}]},"UpperArmL":{"rotate":[{"time":0,"angle":0},{"time":0.1333,"angle":46.49},{"time":0.2667,"angle":122.83},{"time":0.4333,"angle":41.83,"curve":"stepped"},{"time":0.5667,"angle":41.83,"curve":"stepped"},{"time":0.6667,"angle":41.83},{"time":0.7667,"angle":113.93},{"time":1.0333,"angle":0}],"translate":[{"time":0,"x":0,"y":0},{"time":0.1333,"x":-1.27,"y":21.79},{"time":0.2667,"x":-1.02,"y":17.43},{"time":0.4333,"x":-2.84,"y":13.35,"curve":"stepped"},{"time":0.5667,"x":-2.84,"y":13.35,"curve":"stepped"},{"time":0.6667,"x":-2.84,"y":13.35},{"time":0.7667,"x":9.76,"y":-6.42},{"time":1.0333,"x":0,"y":0}]},"LowerArmL":{"rotate":[{"time":0,"angle":0},{"time":0.1333,"angle":-47.06},{"time":0.2667,"angle":-79.46},{"time":0.4333,"angle":-29.61},{"time":0.5667,"angle":-60.48,"curve":"stepped"},{"time":0.6667,"angle":-60.48},{"time":0.7667,"angle":6.48},{"time":1.0333,"angle":0}],"translate":[{"time":0,"x":0,"y":0,"curve":"stepped"},{"time":0.1333,"x":0,"y":0,"curve":"stepped"},{"time":0.2667,"x":0,"y":0,"curve":"stepped"},{"time":0.4333,"x":0,"y":0,"curve":"stepped"},{"time":0.5667,"x":0,"y":0,"curve":"stepped"},{"time":0.6667,"x":0,"y":0,"curve":"stepped"},{"time":1.0333,"x":0,"y":0}]},"Accessery":{"rotate":[{"time":0,"angle":0},{"time":0.1333,"angle":-11.26},{"time":0.2667,"angle":-4.47},{"time":0.4333,"angle":-20.4,"curve":"stepped"},{"time":0.5667,"angle":-20.4,"curve":"stepped"},{"time":0.6667,"angle":-20.4},{"time":0.7667,"angle":20.66},{"time":1.0333,"angle":0}],"translate":[{"time":0,"x":0,"y":0},{"time":0.1333,"x":0,"y":4.18},{"time":0.2667,"x":0,"y":3.35},{"time":0.4333,"x":-16.73,"y":44.33},{"time":0.5667,"x":4.18,"y":23.42,"curve":"stepped"},{"time":0.6667,"x":4.18,"y":23.42},{"time":0.7667,"x":-84.48,"y":16.64},{"time":0.8667,"x":-52.8,"y":73.13},{"time":1.0333,"x":0,"y":0}]},"UpperArmR":{"rotate":[{"time":0,"angle":0},{"time":0.1333,"angle":-3.45},{"time":0.2667,"angle":14.59},{"time":0.4333,"angle":58.34},{"time":0.5667,"angle":-218.15,"curve":"stepped"},{"time":0.6667,"angle":-218.15},{"time":0.7667,"angle":-13.21},{"time":1.0333,"angle":0}],"translate":[{"time":0,"x":0,"y":0,"curve":"stepped"},{"time":0.1333,"x":0,"y":0,"curve":"stepped"},{"time":0.2667,"x":0,"y":0},{"time":0.4333,"x":-15.47,"y":10.52},{"time":0.5667,"x":-23.18,"y":-10.25,"curve":"stepped"},{"time":0.6667,"x":-23.18,"y":-10.25},{"time":0.7667,"x":-8.98,"y":3.64},{"time":1.0333,"x":0,"y":0}]},"LowerArmR":{"rotate":[{"time":0,"angle":-0.24,"curve":"stepped"},{"time":0.2667,"angle":-0.24},{"time":0.4333,"angle":7.32},{"time":0.5667,"angle":4.8,"curve":"stepped"},{"time":0.6667,"angle":4.8},{"time":1.0333,"angle":-0.24}],"translate":[{"time":0,"x":0,"y":0,"curve":"stepped"},{"time":0.2667,"x":0,"y":0,"curve":"stepped"},{"time":1.0333,"x":0,"y":0}]},"WeaponL":{"rotate":[{"time":0,"angle":0},{"time":0.0667,"angle":-50.55},{"time":0.2,"angle":-20.99},{"time":0.2667,"angle":-63.89},{"time":0.4333,"angle":43.5},{"time":0.5667,"angle":16.03,"curve":"stepped"},{"time":0.6667,"angle":16.03},{"time":0.7667,"angle":-27.88},{"time":1.0333,"angle":0}]}}},"Telescope":{"slots":{"Telescope":{"color":[{"time":0,"color":"fffffffe"}]}},"bones":{"UpperArmR":{"rotate":[{"time":0,"angle":104.42},{"time":0.1667,"angle":92.13}],"translate":[{"time":0,"x":-8.79,"y":0.27}]},"UpperArmL":{"rotate":[{"time":0,"angle":-5.29},{"time":0.1667,"angle":4.01}],"translate":[{"time":0,"x":0.27,"y":8.79}]},"Telescope":{"translate":[{"time":0,"x":1.76,"y":-8.79},{"time":0.1667,"x":1.76,"y":-41.31}]},"LowerArmL":{"rotate":[{"time":0,"angle":0},{"time":0.1667,"angle":-26.77}]},"LowerArmR":{"rotate":[{"time":0,"angle":0},{"time":0.1667,"angle":27.55,"curve":"stepped"},{"time":0.5,"angle":27.55}]}}}}}